cordhook/__init__.py
cordhook/embed.py
cordhook/exceptions.py
cordhook/utils.py
cordhook/webhook.py
cordhook-1.0.dist-info/licenses/LICENSE
cordhook-1.0.dist-info/METADATA
cordhook-1.0.dist-info/WHEEL
cordhook-1.0.dist-info/top_level.txt
cordhook-1.0.dist-info/RECORD
